idl_colorbars/__init__.py
idl_colorbars/all_idl_tables.png
idl_colorbars/idl_colorbars.py
idl_colorbars/IDL_rgb_values/000_B-W_LINEAR.dat
idl_colorbars/IDL_rgb_values/001_BLUE-WHITE.dat
idl_colorbars/IDL_rgb_values/002_GRN-RED-BLU-WHT.dat
idl_colorbars/IDL_rgb_values/003_RED_TEMPERATURE.dat
idl_colorbars/IDL_rgb_values/004_BLUE-GREEN-RED-YELLOW.dat
idl_colorbars/IDL_rgb_values/005_STD_GAMMA-II.dat
idl_colorbars/IDL_rgb_values/006_PRISM.dat
idl_colorbars/IDL_rgb_values/007_RED-PURPLE.dat
idl_colorbars/IDL_rgb_values/008_GREEN-WHITE_LINEAR.dat
idl_colorbars/IDL_rgb_values/009_GRN-WHT_EXPONENTIAL.dat
idl_colorbars/IDL_rgb_values/010_GREEN-PINK.dat
idl_colorbars/IDL_rgb_values/011_BLUE-RED.dat
idl_colorbars/IDL_rgb_values/012_16_LEVEL.dat
idl_colorbars/IDL_rgb_values/013_RAINBOW.dat
idl_colorbars/IDL_rgb_values/014_STEPS.dat
idl_colorbars/IDL_rgb_values/015_STERN_SPECIAL.dat
idl_colorbars/IDL_rgb_values/016_Haze.dat
idl_colorbars/IDL_rgb_values/017_Blue_-_Pastel_-_Red.dat
idl_colorbars/IDL_rgb_values/018_Pastels.dat
idl_colorbars/IDL_rgb_values/019_Hue_Sat_Lightness_1.dat
idl_colorbars/IDL_rgb_values/020_Hue_Sat_Lightness_2.dat
idl_colorbars/IDL_rgb_values/021_Hue_Sat_Value_1.dat
idl_colorbars/IDL_rgb_values/022_Hue_Sat_Value_2.dat
idl_colorbars/IDL_rgb_values/023_Purple-Red_plus_Stripes.dat
idl_colorbars/IDL_rgb_values/024_Beach.dat
idl_colorbars/IDL_rgb_values/025_Mac_Style.dat
idl_colorbars/IDL_rgb_values/026_Eos_A.dat
idl_colorbars/IDL_rgb_values/027_Eos_B.dat
idl_colorbars/IDL_rgb_values/028_Hardcandy.dat
idl_colorbars/IDL_rgb_values/029_Nature.dat
idl_colorbars/IDL_rgb_values/030_Ocean.dat
idl_colorbars/IDL_rgb_values/031_Peppermint.dat
idl_colorbars/IDL_rgb_values/032_Plasma.dat
idl_colorbars/IDL_rgb_values/033_Blue-Red.dat
idl_colorbars/IDL_rgb_values/034_Rainbow.dat
idl_colorbars/IDL_rgb_values/035_Blue_Waves.dat
idl_colorbars/IDL_rgb_values/036_Volcano.dat
idl_colorbars/IDL_rgb_values/037_Waves.dat
idl_colorbars/IDL_rgb_values/038_Rainbow18.dat
idl_colorbars-1.1.2.dist-info/LICENSE
idl_colorbars-1.1.2.dist-info/METADATA
idl_colorbars-1.1.2.dist-info/WHEEL
idl_colorbars-1.1.2.dist-info/top_level.txt
idl_colorbars-1.1.2.dist-info/RECORD
