Metadata-Version: 2.1
Name: idl-colorbars
Version: 1.1.2
Summary: Load IDL colormaps into matplotlib.
Home-page: https://github.com/planetarymike/idl-colorbars-python
Author: Mike Chaffin
License: UNKNOWN
Platform: UNKNOWN
Requires-Python: >=3.7
Requires-Dist: numpy (>=1.10)
Requires-Dist: matplotlib (>=3.0.3)
